simplecmd_discordpy/__init__.py
simplecmd_discordpy-2.0.1.dist-info/LICENCE
simplecmd_discordpy-2.0.1.dist-info/METADATA
simplecmd_discordpy-2.0.1.dist-info/WHEEL
simplecmd_discordpy-2.0.1.dist-info/top_level.txt
simplecmd_discordpy-2.0.1.dist-info/RECORD
