Metadata-Version: 2.1
Name: simplecmd_discordpy
Version: 2.0.1
Summary: Uma biblioteca mais simples para a criação de comandos no Discord.py
Author: Anão Lenda
Author-email: 4x0bfuscator@gmail.com
License: MIT
Keywords: simplecmd discordpy comandos
Classifier: Development Status :: 3 - Alpha
Classifier: License :: OSI Approved :: MIT License
Classifier: Programming Language :: Python :: 3
Classifier: Programming Language :: Python :: 3.9
Classifier: Framework :: AsyncIO
Requires-Python: >=3.9
License-File: LICENCE
Requires-Dist: discord
